FiinQuantX/Aggregates.py
FiinQuantX/Aggregates.pyi
FiinQuantX/DateCorr.py
FiinQuantX/DateCorr.pyi
FiinQuantX/Fetch_Trading_Data.py
FiinQuantX/Fetch_Trading_Data.pyi
FiinQuantX/FiinIndicator.py
FiinQuantX/FiinIndicator.pyi
FiinQuantX/FiinQuant.py
FiinQuantX/FiinQuant.pyi
FiinQuantX/GetDataPoint.py
FiinQuantX/GetDataPoint.pyi
FiinQuantX/RealTimeData.py
FiinQuantX/RealTimeData.pyi
FiinQuantX/Rebalance.py
FiinQuantX/Rebalance.pyi
FiinQuantX/SimilarChart.py
FiinQuantX/SimilarChart.pyi
FiinQuantX/Trading_Data_Stream.py
FiinQuantX/Trading_Data_Stream.pyi
FiinQuantX/__init__.py
FiinQuantX/__init__.pyi
fiinquantx-0.1.5.dist-info/METADATA
fiinquantx-0.1.5.dist-info/WHEEL
fiinquantx-0.1.5.dist-info/top_level.txt
fiinquantx-0.1.5.dist-info/RECORD
